<FDM_CONFIG NAME="sgs126" VERSION="1.60">
<!--
  File:     sgs126.xml
  Author:   Aero-Matic v 0.2
  Some tweaks to the Pitch section, Dave Culp
-->
 <METRICS>
   AC_WINGAREA  82.1428571429 
   AC_WINGSPAN  40.0 
   AC_CHORD     2.05357142857 
   AC_HTAILAREA 9.85714285714 
   AC_HTAILARM  11.6875 
   AC_VTAILAREA 8.21428571429 
   AC_LV        12.75 
   AC_IXX       1238.57142857 
   AC_IYY       329.297921317 
   AC_IZZ       1387.36633301 
   AC_IXZ       0 
   AC_EMPTYWT   281.75 
   AC_CGLOC     114.75 0 -6.375 
   AC_AERORP    114.75 0 0 
   AC_EYEPTLOC  48.45 0 9 
 </METRICS>
 <UNDERCARRIAGE>
  AC_GEAR MLG  125.0775 0 -25.5 287.5 57.5 0.5 0.8 0.5 FIXED NONE 0 FIXED
  AC_GEAR NOSE_LG   33.15 0 -15.3 172.5 28.75 0.5 0.8 0.5 STEERABLE NONE 80 FIXED
  AC_GEAR LEFT_WING 114.75 -20 -6.375 172.5 28.75 0.5 0.8 0.5 FIXED NONE 0 FIXED
  AC_GEAR RIGHT_WING 114.75 -20 -6.375 172.5 28.75 0.5 0.8 0.5 FIXED NONE 0 FIXED
 </UNDERCARRIAGE>
 <PROPULSION>
 </PROPULSION>
 <FLIGHT_CONTROL NAME="sgs126">
   <COMPONENT NAME="Pitch Trim Sum" TYPE="SUMMER">
      INPUT   fcs/elevator-cmd-norm
      INPUT   fcs/pitch-trim-cmd-norm
      CLIPTO  -1 1
   </COMPONENT>
   <COMPONENT NAME="Elevator Control" TYPE="AEROSURFACE_SCALE">
      INPUT   fcs/pitch-trim-sum
      MIN     -25
      MAX     35
      GAIN    0.018
      OUTPUT  fcs/elevator-pos-rad
   </COMPONENT>
   <COMPONENT NAME="Roll Trim Sum" TYPE="SUMMER">
      INPUT   fcs/aileron-cmd-norm
      INPUT   fcs/roll-trim-cmd-norm
      CLIPTO  -1 1
   </COMPONENT>
   <COMPONENT NAME="Left Aileron Control" TYPE="AEROSURFACE_SCALE">
      INPUT   fcs/roll-trim-sum
      MIN     -20
      MAX     15
      GAIN    0.02
      OUTPUT  fcs/left-aileron-pos-rad
   </COMPONENT>
   <COMPONENT NAME="Right Aileron Control" TYPE="AEROSURFACE_SCALE">
      INPUT   fcs/roll-trim-sum
      MIN     -20
      MAX     15
      INVERT
      GAIN    0.02
      OUTPUT  fcs/right-aileron-pos-rad
   </COMPONENT>
   <COMPONENT NAME="Yaw Trim Sum" TYPE="SUMMER">
      INPUT   fcs/rudder-cmd-norm
      INPUT   fcs/yaw-trim-cmd-norm
      CLIPTO  -1 1
   </COMPONENT>
   <COMPONENT NAME="Rudder Control" TYPE="AEROSURFACE_SCALE">
      INPUT   fcs/yaw-trim-sum
      MIN     -25
      MAX     25
      GAIN    0.01745
      OUTPUT  fcs/rudder-pos-rad
   </COMPONENT>
   <COMPONENT NAME="Flaps Control" TYPE="KINEMAT">
     INPUT   fcs/flap-cmd-norm
     DETENTS 3
             0   0
             15  2
             30  2
     OUTPUT  fcs/flap-pos-deg
   </COMPONENT>
   <COMPONENT NAME="Gear Control" TYPE="KINEMAT">
     INPUT   gear/gear-cmd-norm
     DETENTS 2
             0   0
             1   5
     OUTPUT  gear/gear-pos-norm
   </COMPONENT>
   <COMPONENT NAME="Speedbrake Control" TYPE="KINEMAT">
     INPUT   fcs/speedbrake-cmd-norm
     DETENTS 2
             0   0
             1   1
     OUTPUT  fcs/speedbrake-pos-norm
   </COMPONENT>
 </FLIGHT_CONTROL>
 <AERODYNAMICS>
  <AXIS NAME="LIFT">
    <COEFFICIENT NAME="CLalpha" TYPE="VECTOR">
      Lift_due_to_alpha
      4
      aero/alpha-rad
      aero/qbar-psf|metrics/Sw-sqft
      -0.10 -0.27
       0.00 0.25
       0.221153846154 1.4
       0.60 0.71
    </COEFFICIENT>
    <COEFFICIENT NAME="dCLflap" TYPE="VALUE">
       Delta_Lift_due_to_flaps
       aero/qbar-psf|metrics/Sw-sqft|fcs/flap-pos-norm
       0.2
    </COEFFICIENT>
    <COEFFICIENT NAME="dCLsb" TYPE="VALUE">
       Delta_Lift_due_to_speedbrake
       aero/qbar-psf|metrics/Sw-sqft|fcs/speedbrake-pos-norm
       -0.05
    </COEFFICIENT>
    <COEFFICIENT NAME="CLde" TYPE="VALUE">
       Lift_due_to_Elevator_Deflection
       aero/qbar-psf|metrics/Sw-sqft|fcs/elevator-pos-rad
       0.2
    </COEFFICIENT>
  </AXIS>
  <AXIS NAME="DRAG">
    <COEFFICIENT NAME="CD0" TYPE="VALUE">
       Drag_at_zero_lift
       aero/qbar-psf|metrics/Sw-sqft
       0.01
    </COEFFICIENT>
    <COEFFICIENT NAME="CDalpha" TYPE="VALUE">
       Drag_due_to_alpha
       aero/qbar-psf|metrics/Sw-sqft|aero/alpha-rad
       0.6
    </COEFFICIENT>
    <COEFFICIENT NAME="CDmach" TYPE="VECTOR">
       Drag_due_to_mach
       4
       velocities/mach-norm
       aero/qbar-psf|metrics/Sw-sqft
       0.0       0.00
       0.7     0.00
       1.1       0.02
       2.0       0.01
    </COEFFICIENT>
    <COEFFICIENT NAME="CDflap" TYPE="VALUE">
       Drag_due_to_flaps
       aero/qbar-psf|metrics/Sw-sqft|fcs/flap-pos-norm
       0.03
    </COEFFICIENT>
    <COEFFICIENT NAME="CDgear" TYPE="VALUE">
       Drag_due_to_gear
       aero/qbar-psf|metrics/Sw-sqft|gear/gear-pos-norm
       0.00
    </COEFFICIENT>
    <COEFFICIENT NAME="CDsb" TYPE="VALUE">
       Drag_due_to_speedbrakes
       aero/qbar-psf|metrics/Sw-sqft|fcs/speedbrake-pos-norm
       0.01
    </COEFFICIENT>
    <COEFFICIENT NAME="CDbeta" TYPE="VALUE">
       Drag_due_to_sideslip
       aero/qbar-psf|metrics/Sw-sqft|aero/beta-rad
       0.2
    </COEFFICIENT>
    <COEFFICIENT NAME="CDde" TYPE="VALUE">
       Drag_due_to_Elevator_Deflection
       aero/qbar-psf|metrics/Sw-sqft|fcs/elevator-pos-norm
       0.03
    </COEFFICIENT>
  </AXIS>
  <AXIS NAME="SIDE">
    <COEFFICIENT NAME="CSb" TYPE="VALUE">
       Side_force_due_to_beta
       aero/qbar-psf|metrics/Sw-sqft|aero/beta-rad
       -1.5
    </COEFFICIENT>
  </AXIS>
  <AXIS NAME="ROLL">
    <COEFFICIENT NAME="Clb" TYPE="VALUE">
       Roll_moment_due_to_beta
       aero/qbar-psf|metrics/Sw-sqft|metrics/bw-ft|aero/beta-rad
       -0.01
    </COEFFICIENT>
    <COEFFICIENT NAME="Clp" TYPE="VALUE">
       Roll_moment_due_to_roll_rate
       aero/qbar-psf|metrics/Sw-sqft|metrics/bw-ft|aero/bi2vel|velocities/p-aero-rad_sec
       -0.5
    </COEFFICIENT>
    <COEFFICIENT NAME="Clr" TYPE="VALUE">
       Roll_moment_due_to_yaw_rate
       aero/qbar-psf|metrics/Sw-sqft|metrics/bw-ft|aero/bi2vel|velocities/r-aero-rad_sec
       0.1
    </COEFFICIENT>
    <COEFFICIENT NAME="Clda" TYPE="VALUE">
       Roll_moment_due_to_aileron
       aero/qbar-psf|metrics/Sw-sqft|metrics/bw-ft|fcs/left-aileron-pos-rad
       0.06
    </COEFFICIENT>
    <COEFFICIENT NAME="Cldr" TYPE="VALUE">
       Roll_moment_due_to_rudder
       aero/qbar-psf|metrics/Sw-sqft|metrics/bw-ft|fcs/rudder-pos-rad
       0.005
    </COEFFICIENT>
  </AXIS>
  <AXIS NAME="PITCH">
    <COEFFICIENT NAME="Cmalpha" TYPE="VALUE">
       Pitch_moment_due_to_alpha
       aero/qbar-psf|metrics/Sw-sqft|metrics/cbarw-ft|aero/alpha-rad
       -1.5
    </COEFFICIENT>
    <COEFFICIENT NAME="Cmde" TYPE="VALUE">
       Pitch_moment_due_to_elevator
       aero/qbar-psf|metrics/Sw-sqft|metrics/cbarw-ft|fcs/elevator-pos-rad
       -0.4
    </COEFFICIENT>
    <COEFFICIENT NAME="Cmq" TYPE="VALUE">
       Pitch_moment_due_to_pitch_rate
       aero/qbar-psf|metrics/Sw-sqft|metrics/cbarw-ft|aero/ci2vel|velocities/q-aero-rad_sec
       -6
    </COEFFICIENT>
    <COEFFICIENT NAME="Cmadot" TYPE="VALUE">
       Pitch_moment_due_to_alpha_rate
       aero/qbar-psf|metrics/Sw-sqft|metrics/cbarw-ft|aero/ci2vel|aero/alphadot-rad_sec
       -1
    </COEFFICIENT>
  </AXIS>
  <AXIS NAME="YAW">
    <COEFFICIENT NAME="Cnb" TYPE="VALUE">
       Yaw_moment_due_to_beta
       aero/qbar-psf|metrics/Sw-sqft|metrics/bw-ft|aero/beta-rad
       0.16
    </COEFFICIENT>
    <COEFFICIENT NAME="Cnr" TYPE="VALUE">
       Yaw_moment_due_to_yaw_rate
       aero/qbar-psf|metrics/Sw-sqft|metrics/bw-ft|aero/bi2vel|velocities/r-aero-rad_sec
       -0.04
    </COEFFICIENT>
    <COEFFICIENT NAME="Cndr" TYPE="VALUE">
       Yaw_moment_due_to_rudder
       aero/qbar-psf|metrics/Sw-sqft|metrics/bw-ft|fcs/rudder-pos-rad
       -0.03
    </COEFFICIENT>
    <COEFFICIENT NAME="Cnda" TYPE="VALUE">
       Adverse_yaw
       aero/qbar-psf|metrics/Sw-sqft|metrics/bw-ft|fcs/left-aileron-pos-rad
       -0.02
    </COEFFICIENT>
  </AXIS>
 </AERODYNAMICS>
</FDM_CONFIG>
